setup.py
hkshiteshpkgtest/__init__.py
hkshiteshpkgtest/calculator.py
hkshiteshpkgtest.egg-info/PKG-INFO
hkshiteshpkgtest.egg-info/SOURCES.txt
hkshiteshpkgtest.egg-info/dependency_links.txt
hkshiteshpkgtest.egg-info/top_level.txt